{
  "/_not-found/page": "app/_not-found/page.js",
  "/2fa/page": "app/2fa/page.js",
  "/forgot-password/page": "app/forgot-password/page.js",
  "/admin/login/page": "app/admin/login/page.js",
  "/perfil/completar/page": "app/perfil/completar/page.js",
  "/debug/page": "app/debug/page.js",
  "/request-access/page": "app/request-access/page.js",
  "/reset-password/page": "app/reset-password/page.js",
  "/page": "app/page.js",
  "/(admin)/admin/jobs/[id]/edit/page": "app/(admin)/admin/jobs/[id]/edit/page.js",
  "/(admin)/admin/jobs/[id]/kanban/page": "app/(admin)/admin/jobs/[id]/kanban/page.js",
  "/(admin)/admin/dashboard/page": "app/(admin)/admin/dashboard/page.js",
  "/(admin)/admin/jobs/new/page": "app/(admin)/admin/jobs/new/page.js",
  "/(admin)/admin/roles/[id]/edit/page": "app/(admin)/admin/roles/[id]/edit/page.js",
  "/(admin)/admin/jobs/page": "app/(admin)/admin/jobs/page.js",
  "/(admin)/admin/roles/new/page": "app/(admin)/admin/roles/new/page.js",
  "/(admin)/admin/audit/page": "app/(admin)/admin/audit/page.js",
  "/(admin)/admin/roles/page": "app/(admin)/admin/roles/page.js",
  "/(admin)/admin/jobs/[id]/page": "app/(admin)/admin/jobs/[id]/page.js",
  "/(admin)/admin/settings/page": "app/(admin)/admin/settings/page.js",
  "/(admin)/admin/settings/users/[id]/edit/page": "app/(admin)/admin/settings/users/[id]/edit/page.js",
  "/(candidate)/candidate/dashboard/page": "app/(candidate)/candidate/dashboard/page.js",
  "/(candidate)/candidate/applications/page": "app/(candidate)/candidate/applications/page.js",
  "/(candidate)/candidate/settings/page": "app/(candidate)/candidate/settings/page.js",
  "/(public)/login/page": "app/(public)/login/page.js",
  "/(candidate)/candidate/applications/[id]/page": "app/(candidate)/candidate/applications/[id]/page.js",
  "/(public)/recuperar-senha/page": "app/(public)/recuperar-senha/page.js",
  "/(admin)/admin/talent-bank/page": "app/(admin)/admin/talent-bank/page.js",
  "/(candidate)/candidate/saved-jobs/page": "app/(candidate)/candidate/saved-jobs/page.js",
  "/(public)/redefinir-senha/page": "app/(public)/redefinir-senha/page.js",
  "/(public)/privacidade/page": "app/(public)/privacidade/page.js",
  "/(public)/cadastro/page": "app/(public)/cadastro/page.js",
  "/(public)/vagas/page": "app/(public)/vagas/page.js",
  "/(public)/cadastro/candidato/page": "app/(public)/cadastro/candidato/page.js",
  "/(public)/cadastro/empresa/page": "app/(public)/cadastro/empresa/page.js",
  "/(public)/verificar-email/page": "app/(public)/verificar-email/page.js",
  "/(public)/vagas/[slug]/[id]/page": "app/(public)/vagas/[slug]/[id]/page.js",
  "/(superadmin)/super-admin/companies/[id]/page": "app/(superadmin)/super-admin/companies/[id]/page.js",
  "/(public)/termos/page": "app/(public)/termos/page.js",
  "/(public)/vagas/[slug]/[id]/candidatar/page": "app/(public)/vagas/[slug]/[id]/candidatar/page.js",
  "/(public)/vagas/[slug]/page": "app/(public)/vagas/[slug]/page.js",
  "/(superadmin)/super-admin/jobs/page": "app/(superadmin)/super-admin/jobs/page.js",
  "/(superadmin)/super-admin/talent-bank/page": "app/(superadmin)/super-admin/talent-bank/page.js",
  "/(superadmin)/super-admin/audit/page": "app/(superadmin)/super-admin/audit/page.js",
  "/(superadmin)/super-admin/dashboard/page": "app/(superadmin)/super-admin/dashboard/page.js",
  "/(superadmin)/super-admin/roles/page": "app/(superadmin)/super-admin/roles/page.js",
  "/(superadmin)/super-admin/settings/page": "app/(superadmin)/super-admin/settings/page.js",
  "/(superadmin)/super-admin/overview/page": "app/(superadmin)/super-admin/overview/page.js"
}